{
  "locations" : [ {
    "id" : 190951,
    "name" : "Siegfried Theiss-Straße 9",
    "address" : "Siegfried Theiss-Straße 9",
    "location" : "47.7831390,16.2297740",
    "zones" : [ {
      "evses" : [ {
        "id" : "565940",
        "identifier" : "AT*EVN*E3801*2",
        "networkId" : "1",
        "maxPower" : 11000,
        "currentType" : "ac",
        "status" : "available",
        "managedByOperator" : true,
        "reservationMinutes" : 0,
        "isAvailable" : true,
        "tariffId" : "491",
        "connectors" : [ {
          "name" : "Type 2",
          "icon" : "type2",
          "format" : "socket",
          "status" : "active"
        } ],
        "roamingEvseId" : "AT*EVN*E3801*2",
        "qrUrl" : "https://cp.emobility.gremonaelektriko.si/public/cs/AT*EVN*E3801*2",
        "capabilities" : "REMOTE_START_STOP_CAPABLE,METER_VALUES",
        "hasParkingBarrier" : false,
        "canReserve" : false,
        "isTemporarilyUnavailable" : false,
        "isLongTermUnavailable" : false
      }, {
        "id" : "565941",
        "identifier" : "AT*EVN*E3801*1",
        "networkId" : "2",
        "maxPower" : 11000,
        "currentType" : "ac",
        "status" : "available",
        "managedByOperator" : true,
        "reservationMinutes" : 0,
        "isAvailable" : true,
        "tariffId" : "491",
        "connectors" : [ {
          "name" : "Type 2",
          "icon" : "type2",
          "format" : "socket",
          "status" : "active"
        } ],
        "roamingEvseId" : "AT*EVN*E3801*1",
        "qrUrl" : "https://cp.emobility.gremonaelektriko.si/public/cs/AT*EVN*E3801*1",
        "capabilities" : "REMOTE_START_STOP_CAPABLE,METER_VALUES",
        "hasParkingBarrier" : false,
        "canReserve" : false,
        "isTemporarilyUnavailable" : false,
        "isLongTermUnavailable" : false
      }, {
        "id" : "565942",
        "identifier" : "AT*EVN*E3800*2",
        "networkId" : "3",
        "maxPower" : 11000,
        "currentType" : "ac",
        "status" : "available",
        "managedByOperator" : true,
        "reservationMinutes" : 0,
        "isAvailable" : true,
        "tariffId" : "491",
        "connectors" : [ {
          "name" : "Type 2",
          "icon" : "type2",
          "format" : "socket",
          "status" : "active"
        } ],
        "roamingEvseId" : "AT*EVN*E3800*2",
        "qrUrl" : "https://cp.emobility.gremonaelektriko.si/public/cs/AT*EVN*E3800*2",
        "capabilities" : "REMOTE_START_STOP_CAPABLE,METER_VALUES",
        "hasParkingBarrier" : false,
        "canReserve" : false,
        "isTemporarilyUnavailable" : false,
        "isLongTermUnavailable" : false
      }, {
        "id" : "565943",
        "identifier" : "AT*EVN*E3800*1",
        "networkId" : "4",
        "maxPower" : 11000,
        "currentType" : "ac",
        "status" : "available",
        "managedByOperator" : true,
        "reservationMinutes" : 0,
        "isAvailable" : true,
        "tariffId" : "491",
        "connectors" : [ {
          "name" : "Type 2",
          "icon" : "type2",
          "format" : "socket",
          "status" : "active"
        } ],
        "roamingEvseId" : "AT*EVN*E3800*1",
        "qrUrl" : "https://cp.emobility.gremonaelektriko.si/public/cs/AT*EVN*E3800*1",
        "capabilities" : "REMOTE_START_STOP_CAPABLE,METER_VALUES",
        "hasParkingBarrier" : false,
        "canReserve" : false,
        "isTemporarilyUnavailable" : false,
        "isLongTermUnavailable" : false
      } ]
    } ],
    "updatedAt" : "2024-08-06 03:38:09.000",
    "timezone" : "Europe/Ljubljana"
  } ]
}