{
  "locations" : [ {
    "id" : 371145,
    "name" : "Riko, d.o.o.",
    "address" : "Bizjanova ulica 2",
    "location" : "46.0675267,14.4802336",
    "zones" : [ {
      "evses" : [ {
        "id" : "738098",
        "identifier" : "3851",
        "networkId" : "1",
        "maxPower" : 22000,
        "currentType" : "ac",
        "status" : "available",
        "managedByOperator" : true,
        "reservationMinutes" : 0,
        "isAvailable" : true,
        "tariffId" : "838",
        "connectors" : [ {
          "name" : "Type 2",
          "icon" : "type2",
          "format" : "cable",
          "status" : "active"
        } ],
        "roamingEvseId" : null,
        "qrUrl" : "https://cp.emobility.megatel.si/public/cs/3851",
        "capabilities" : "REMOTE_START_STOP_CAPABLE,METER_VALUES,STOP_TRANSACTION_ON_EV_DISCONNECT",
        "hasParkingBarrier" : false,
        "canReserve" : false,
        "isTemporarilyUnavailable" : false,
        "isLongTermUnavailable" : false
      }, {
        "id" : "738099",
        "identifier" : "8048",
        "networkId" : "2",
        "maxPower" : 50000,
        "currentType" : "dc",
        "status" : "available",
        "managedByOperator" : true,
        "reservationMinutes" : 0,
        "isAvailable" : true,
        "tariffId" : "839",
        "connectors" : [ {
          "name" : "CCS 2",
          "icon" : "ccs2",
          "format" : "cable",
          "status" : "active"
        } ],
        "roamingEvseId" : null,
        "qrUrl" : "https://cp.emobility.megatel.si/public/cs/8048",
        "capabilities" : "REMOTE_START_STOP_CAPABLE,METER_VALUES,STOP_TRANSACTION_ON_EV_DISCONNECT",
        "hasParkingBarrier" : false,
        "canReserve" : false,
        "isTemporarilyUnavailable" : false,
        "isLongTermUnavailable" : false
      } ]
    } ],
    "updatedAt" : "2024-06-06 07:58:48.000",
    "timezone" : "Europe/Ljubljana"
  } ]
}