{
  "locations" : [ {
    "id" : 208322,
    "name" : "Pristava Krapinska 63 ",
    "address" : "Pristava Krapinska 63 ",
    "location" : "46.1445220,15.8730420",
    "zones" : [ {
      "evses" : [ {
        "id" : "609654",
        "identifier" : "HR*QLO*EAC000138",
        "networkId" : "1",
        "maxPower" : 22000,
        "currentType" : "ac",
        "status" : "available",
        "managedByOperator" : true,
        "reservationMinutes" : 0,
        "isAvailable" : true,
        "tariffId" : "650",
        "connectors" : [ {
          "name" : "Type 2",
          "icon" : "type2",
          "format" : "socket",
          "status" : "active"
        } ],
        "roamingEvseId" : "HR*QLO*EAC000138",
        "qrUrl" : "https://cp.charge.efrend.si/public/cs/HR*QLO*EAC000138",
        "capabilities" : "REMOTE_START_STOP_CAPABLE,METER_VALUES",
        "hasParkingBarrier" : false,
        "canReserve" : false,
        "isTemporarilyUnavailable" : false,
        "isLongTermUnavailable" : false
      } ]
    } ],
    "updatedAt" : "2024-11-07 05:06:49.000",
    "timezone" : "Europe/Ljubljana"
  }, {
    "id" : 208382,
    "name" : "Pristava Krapinska 63 ",
    "address" : "Pristava Krapinska 63 ",
    "location" : "46.1445270,15.8730530",
    "zones" : [ {
      "evses" : [ {
        "id" : "609708",
        "identifier" : "HR*QLO*EAC000139",
        "networkId" : "1",
        "maxPower" : 22000,
        "currentType" : "ac",
        "status" : "available",
        "managedByOperator" : true,
        "reservationMinutes" : 0,
        "isAvailable" : true,
        "tariffId" : "650",
        "connectors" : [ {
          "name" : "Type 2",
          "icon" : "type2",
          "format" : "socket",
          "status" : "active"
        } ],
        "roamingEvseId" : "HR*QLO*EAC000139",
        "qrUrl" : "https://cp.charge.efrend.si/public/cs/HR*QLO*EAC000139",
        "capabilities" : "REMOTE_START_STOP_CAPABLE,METER_VALUES",
        "hasParkingBarrier" : false,
        "canReserve" : false,
        "isTemporarilyUnavailable" : false,
        "isLongTermUnavailable" : false
      } ]
    } ],
    "updatedAt" : "2024-11-07 05:06:49.000",
    "timezone" : "Europe/Ljubljana"
  }, {
    "id" : 211665,
    "name" : "Rathausplatz 1",
    "address" : "Rathausplatz 1",
    "location" : "47.8783230,14.1321310",
    "zones" : [ {
      "evses" : [ {
        "id" : "621898",
        "identifier" : "AT*ENA*E02804",
        "networkId" : "1",
        "maxPower" : 22000,
        "currentType" : "ac",
        "status" : "charging",
        "managedByOperator" : true,
        "reservationMinutes" : 0,
        "isAvailable" : false,
        "tariffId" : "373",
        "connectors" : [ {
          "name" : "Type 2",
          "icon" : "type2",
          "format" : "socket",
          "status" : "active"
        } ],
        "roamingEvseId" : "AT*ENA*E02804",
        "qrUrl" : "https://cp.charge.efrend.si/public/cs/AT*ENA*E02804",
        "capabilities" : "REMOTE_START_STOP_CAPABLE,METER_VALUES",
        "hasParkingBarrier" : false,
        "canReserve" : false,
        "isTemporarilyUnavailable" : false,
        "isLongTermUnavailable" : false
      } ]
    } ],
    "updatedAt" : "2024-11-19 03:51:40.000",
    "timezone" : "Europe/Ljubljana"
  }, {
    "id" : 211666,
    "name" : "Weiberfelderweg 1",
    "address" : "Weiberfelderweg 1",
    "location" : "47.0276820,15.4004910",
    "zones" : [ {
      "evses" : [ {
        "id" : "621899",
        "identifier" : "AT*EST*E000*03195",
        "networkId" : "1",
        "maxPower" : 25000,
        "currentType" : "dc",
        "status" : "available",
        "managedByOperator" : true,
        "reservationMinutes" : 0,
        "isAvailable" : true,
        "tariffId" : "345",
        "connectors" : [ {
          "name" : "CCS 2",
          "icon" : "ccs2",
          "format" : "cable",
          "status" : "active"
        } ],
        "roamingEvseId" : "AT*EST*E000*03195",
        "qrUrl" : "https://cp.charge.efrend.si/public/cs/AT*EST*E000*03195",
        "capabilities" : "REMOTE_START_STOP_CAPABLE,METER_VALUES",
        "hasParkingBarrier" : false,
        "canReserve" : false,
        "isTemporarilyUnavailable" : false,
        "isLongTermUnavailable" : false
      }, {
        "id" : "621900",
        "identifier" : "AT*EST*E000*03194",
        "networkId" : "2",
        "maxPower" : 25000,
        "currentType" : "dc",
        "status" : "available",
        "managedByOperator" : true,
        "reservationMinutes" : 0,
        "isAvailable" : true,
        "tariffId" : "345",
        "connectors" : [ {
          "name" : "CCS 2",
          "icon" : "ccs2",
          "format" : "cable",
          "status" : "active"
        } ],
        "roamingEvseId" : "AT*EST*E000*03194",
        "qrUrl" : "https://cp.charge.efrend.si/public/cs/AT*EST*E000*03194",
        "capabilities" : "REMOTE_START_STOP_CAPABLE,METER_VALUES",
        "hasParkingBarrier" : false,
        "canReserve" : false,
        "isTemporarilyUnavailable" : false,
        "isLongTermUnavailable" : false
      } ]
    } ],
    "updatedAt" : "2024-11-19 03:51:46.000",
    "timezone" : "Europe/Ljubljana"
  }, {
    "id" : 211667,
    "name" : "Kainachtalstraße 9",
    "address" : "Kainachtalstraße 9",
    "location" : "46.8866730,15.5010840",
    "zones" : [ {
      "evses" : [ {
        "id" : "621901",
        "identifier" : "AT*EST*E000*03239",
        "networkId" : "1",
        "maxPower" : 25000,
        "currentType" : "dc",
        "status" : "available",
        "managedByOperator" : true,
        "reservationMinutes" : 0,
        "isAvailable" : true,
        "tariffId" : "345",
        "connectors" : [ {
          "name" : "CCS 2",
          "icon" : "ccs2",
          "format" : "cable",
          "status" : "active"
        } ],
        "roamingEvseId" : "AT*EST*E000*03239",
        "qrUrl" : "https://cp.charge.efrend.si/public/cs/AT*EST*E000*03239",
        "capabilities" : "REMOTE_START_STOP_CAPABLE,METER_VALUES",
        "hasParkingBarrier" : false,
        "canReserve" : false,
        "isTemporarilyUnavailable" : false,
        "isLongTermUnavailable" : false
      }, {
        "id" : "621902",
        "identifier" : "AT*EST*E000*03238",
        "networkId" : "2",
        "maxPower" : 25000,
        "currentType" : "dc",
        "status" : "available",
        "managedByOperator" : true,
        "reservationMinutes" : 0,
        "isAvailable" : true,
        "tariffId" : "345",
        "connectors" : [ {
          "name" : "CCS 2",
          "icon" : "ccs2",
          "format" : "cable",
          "status" : "active"
        } ],
        "roamingEvseId" : "AT*EST*E000*03238",
        "qrUrl" : "https://cp.charge.efrend.si/public/cs/AT*EST*E000*03238",
        "capabilities" : "REMOTE_START_STOP_CAPABLE,METER_VALUES",
        "hasParkingBarrier" : false,
        "canReserve" : false,
        "isTemporarilyUnavailable" : false,
        "isLongTermUnavailable" : false
      }, {
        "id" : "621903",
        "identifier" : "AT*EST*E000*03237",
        "networkId" : "3",
        "maxPower" : 25000,
        "currentType" : "dc",
        "status" : "available",
        "managedByOperator" : true,
        "reservationMinutes" : 0,
        "isAvailable" : true,
        "tariffId" : "345",
        "connectors" : [ {
          "name" : "CCS 2",
          "icon" : "ccs2",
          "format" : "cable",
          "status" : "active"
        } ],
        "roamingEvseId" : "AT*EST*E000*03237",
        "qrUrl" : "https://cp.charge.efrend.si/public/cs/AT*EST*E000*03237",
        "capabilities" : "REMOTE_START_STOP_CAPABLE,METER_VALUES",
        "hasParkingBarrier" : false,
        "canReserve" : false,
        "isTemporarilyUnavailable" : false,
        "isLongTermUnavailable" : false
      }, {
        "id" : "621904",
        "identifier" : "AT*EST*E000*03236",
        "networkId" : "4",
        "maxPower" : 25000,
        "currentType" : "dc",
        "status" : "available",
        "managedByOperator" : true,
        "reservationMinutes" : 0,
        "isAvailable" : true,
        "tariffId" : "345",
        "connectors" : [ {
          "name" : "CCS 2",
          "icon" : "ccs2",
          "format" : "cable",
          "status" : "active"
        } ],
        "roamingEvseId" : "AT*EST*E000*03236",
        "qrUrl" : "https://cp.charge.efrend.si/public/cs/AT*EST*E000*03236",
        "capabilities" : "REMOTE_START_STOP_CAPABLE,METER_VALUES",
        "hasParkingBarrier" : false,
        "canReserve" : false,
        "isTemporarilyUnavailable" : false,
        "isLongTermUnavailable" : false
      }, {
        "id" : "621905",
        "identifier" : "AT*EST*E000*03197",
        "networkId" : "5",
        "maxPower" : 75000,
        "currentType" : "dc",
        "status" : "available",
        "managedByOperator" : true,
        "reservationMinutes" : 0,
        "isAvailable" : true,
        "tariffId" : "345",
        "connectors" : [ {
          "name" : "CCS 2",
          "icon" : "ccs2",
          "format" : "cable",
          "status" : "active"
        } ],
        "roamingEvseId" : "AT*EST*E000*03197",
        "qrUrl" : "https://cp.charge.efrend.si/public/cs/AT*EST*E000*03197",
        "capabilities" : "REMOTE_START_STOP_CAPABLE,METER_VALUES",
        "hasParkingBarrier" : false,
        "canReserve" : false,
        "isTemporarilyUnavailable" : false,
        "isLongTermUnavailable" : false
      }, {
        "id" : "621906",
        "identifier" : "AT*EST*E000*03196",
        "networkId" : "1",
        "maxPower" : 75000,
        "currentType" : "dc",
        "status" : "available",
        "managedByOperator" : true,
        "reservationMinutes" : 0,
        "isAvailable" : true,
        "tariffId" : "345",
        "connectors" : [ {
          "name" : "CCS 2",
          "icon" : "ccs2",
          "format" : "cable",
          "status" : "active"
        } ],
        "roamingEvseId" : "AT*EST*E000*03196",
        "qrUrl" : "https://cp.charge.efrend.si/public/cs/AT*EST*E000*03196",
        "capabilities" : "REMOTE_START_STOP_CAPABLE,METER_VALUES",
        "hasParkingBarrier" : false,
        "canReserve" : false,
        "isTemporarilyUnavailable" : false,
        "isLongTermUnavailable" : false
      } ]
    } ],
    "updatedAt" : "2024-11-19 03:51:47.000",
    "timezone" : "Europe/Ljubljana"
  }, {
    "id" : 211668,
    "name" : "Gewerbestraße 16",
    "address" : "Gewerbestraße 16",
    "location" : "47.8583760,13.1319560",
    "zones" : [ {
      "evses" : [ {
        "id" : "621907",
        "identifier" : "CH*ECUERXZWDKYACGC5JDRCYEDYHHFRMQ",
        "networkId" : "1",
        "maxPower" : 11000,
        "currentType" : "ac",
        "status" : "available",
        "managedByOperator" : true,
        "reservationMinutes" : 0,
        "isAvailable" : true,
        "tariffId" : "419",
        "connectors" : [ {
          "name" : "Type 2",
          "icon" : "type2",
          "format" : "socket",
          "status" : "active"
        } ],
        "roamingEvseId" : "CH*ECUERXZWDKYACGC5JDRCYEDYHHFRMQ",
        "qrUrl" : "https://cp.charge.efrend.si/public/cs/CH*ECUERXZWDKYACGC5JDRCYEDYHHFRMQ",
        "capabilities" : "REMOTE_START_STOP_CAPABLE,METER_VALUES",
        "hasParkingBarrier" : false,
        "canReserve" : false,
        "isTemporarilyUnavailable" : false,
        "isLongTermUnavailable" : false
      } ]
    } ],
    "updatedAt" : "2024-11-19 03:56:32.000",
    "timezone" : "Europe/Ljubljana"
  }, {
    "id" : 211669,
    "name" : "Gewerbestraße 16",
    "address" : "Gewerbestraße 16",
    "location" : "47.8583990,13.1319560",
    "zones" : [ {
      "evses" : [ {
        "id" : "621908",
        "identifier" : "CH*ECUEQNS45RAGTQ8FLW6HGEMRGAYCGZ",
        "networkId" : "1",
        "maxPower" : 11000,
        "currentType" : "ac",
        "status" : "available",
        "managedByOperator" : true,
        "reservationMinutes" : 0,
        "isAvailable" : true,
        "tariffId" : "419",
        "connectors" : [ {
          "name" : "Type 2",
          "icon" : "type2",
          "format" : "socket",
          "status" : "active"
        } ],
        "roamingEvseId" : "CH*ECUEQNS45RAGTQ8FLW6HGEMRGAYCGZ",
        "qrUrl" : "https://cp.charge.efrend.si/public/cs/CH*ECUEQNS45RAGTQ8FLW6HGEMRGAYCGZ",
        "capabilities" : "REMOTE_START_STOP_CAPABLE,METER_VALUES",
        "hasParkingBarrier" : false,
        "canReserve" : false,
        "isTemporarilyUnavailable" : false,
        "isLongTermUnavailable" : false
      } ]
    } ],
    "updatedAt" : "2024-11-19 03:56:33.000",
    "timezone" : "Europe/Ljubljana"
  } ]
}